{
  "windows": {
    "train": [
      "2024-11-06",
      "2026-01-16"
    ],
    "validate": [
      "2026-01-19",
      "2026-07-23"
    ]
  },
  "params_used": {
    "BUY_SCORE": 70,
    "STOP_ATR_MULT": 2.5,
    "TRAIL_ATR_MULT": 4.0
  },
  "train": {
    "trades": 50,
    "win_rate": 46.0,
    "avg_win": 13201.0,
    "avg_loss": -4287.0,
    "profit_factor": 2.62,
    "expectancy_R": 0.386,
    "avg_hold_days": 29.2,
    "total_return_pct": 22.6,
    "annualized_pct": 18.8,
    "max_drawdown_pct": -7.2
  },
  "train_exit_breakdown": {
    "end of test": {
      "n": 5,
      "avg_R": 1.62
    },
    "score decay": {
      "n": 12,
      "avg_R": -0.27
    },
    "stop": {
      "n": 23,
      "avg_R": 0.09
    },
    "stop (gap)": {
      "n": 3,
      "avg_R": -1.26
    },
    "time stop": {
      "n": 7,
      "avg_R": 2.32
    }
  },
  "validate": {
    "trades": 0
  },
  "validate_exit_breakdown": {}
}